{
  "enabled": true,
  "context": "client",
  "identifier": "com.pa.samzlx.kappacommander",
  "display_name": "Strategic Kappa Icon - Commander",
  "description": "Make your commander a Kappa",
  "author": "samzlx, dom314",
  "version": "1.2.0",
  "build": "99377",
  "date": "2017/1/17",
  "signature": "not yet implemented",
  "category": [
        "in-game",
        "client-mod",
        "Strategic-icons"
    ],
  "forum": "https://forums.uberent.com/threads/rel-client-strategic-kappa-icon-commander.71368/",
  "icon": "http://i.imgur.com/EF9fHDO.gif",
  "priority": 101
}
